apitools/__init__.py
apitools/config.py
apitools/main.py
apitools/process.py
apitools/py.typed
mtssoft_openapi_tools-0.1.0.dist-info/METADATA
mtssoft_openapi_tools-0.1.0.dist-info/WHEEL
mtssoft_openapi_tools-0.1.0.dist-info/entry_points.txt
mtssoft_openapi_tools-0.1.0.dist-info/RECORD
