Metadata-Version: 2.3
Name: mtssoft-openapi-tools
Version: 0.1.0
Summary: 
Requires-Python: >=3.13,<4.0
Classifier: Programming Language :: Python :: 3
Classifier: Programming Language :: Python :: 3.13
Requires-Dist: httpx (>=0.28.1,<0.29.0)
Requires-Dist: openapi-pydantic (>=0.5.1,<0.6.0)
Requires-Dist: pydantic (>=2.11.7,<3.0.0)
Requires-Dist: toml (>=0.10.2,<0.11.0)
Requires-Dist: typer (>=0.16.0,<0.17.0)
